{
  "followers": [
    "franeckk",
    "truposz92",
    "kiddeath77",
    "depesheee",
    "saas6887",
    "kotex33",
    "sezar2021",
    "dodfalkor",
    "habababa187",
    "mrgambz",
    "ariulpl",
    "friendlyghost92",
    "huntertreserpunter",
    "magik12122",
    "glidiaa",
    "tgmstackman",
    "midlifecrisiscod",
    "bartek1543",
    "forspokeniscoming",
    "kingmichrvy",
    "dc_girly",
    "mrevek",
    "ikiingslayer",
    "reallylikedrugs",
    "life_wow",
    "purpleprincess85",
    "szkl0k",
    "icequeen997",
    "lesny33",
    "m0rtemik",
    "nocny_wilczek",
    "waterjeff",
    "klaudenx",
    "icequeen937",
    "kraftur_",
    "akkarin_75",
    "zjemcidzem00",
    "brain_teaser01",
    "siwyseqe",
    "babygroguxd",
    "jackieshan1200",
    "txjezzle",
    "kranikbot",
    "kubson3k",
    "borellusborealis",
    "meo139",
    "bluekage101",
    "szamanojke",
    "peletronix",
    "szo3k",
    "scorpioneroo",
    "seksownaeklerka",
    "magdanik93",
    "brain_teaser0",
    "reeleebaad",
    "feleysa",
    "luksor_foreveryou",
    "c_k1000",
    "brkgametv",
    "rothgar_wilk",
    "beliareth",
    "kasumi530",
    "the_finals_clipz",
    "l0rdgtr",
    "tor_nado_slimak",
    "dandi__99",
    "bolec8900",
    "moniabjw",
    "sniffurious",
    "matwiejkamil",
    "tjoepe",
    "abulletcash4",
    "annabaybee2",
    "kidddagawd",
    "natalia608",
    "the_green_flash__",
    "janciolapserdak",
    "mikolajvlogv2",
    "ravek162",
    "k4muto",
    "mumins24",
    "xxxrumcajsxxx",
    "danielchristopherasfd",
    "mojeoko",
    "juuxxyy",
    "spark1gee",
    "ranlosin",
    "khalmysan",
    "xdr_killer_",
    "donell_007",
    "agamalaga1",
    "manufaq",
    "voiciehh",
    "emmanuel_gaming420",
    "krokers22",
    "panpawel25",
    "drhero123",
    "maxsixtw",
    "szulu11999933",
    "sushi_chef_kielbi",
    "maciejmvp",
    "kot_szen",
    "tabularaza92",
    "alcarvee",
    "iuni69",
    "whitebeowulf",
    "z4kuhs",
    "kawoszyt12",
    "hunnibuntv",
    "xmateqqx",
    "mr_vifon",
    "nvrmind211",
    "xxuszatyxx",
    "g00dvib3z",
    "hatredczech",
    "russian_592",
    "tojamaksiu33",
    "almightly",
    "zabaranowska",
    "kretospl",
    "gastrolimpo",
    "evilyurii",
    "estus2137",
    "ahmettdursun",
    "matthewpiter95",
    "gtorchh",
    "rhazielo",
    "mtb_j4kub",
    "xarbit",
    "sonixx2111",
    "mileslaw7",
    "rafnexx",
    "adekz",
    "byybybyy",
    "memr_mleko",
    "bamek_",
    "getosuguru12",
    "palka666666",
    "lukee997",
    "borsukee",
    "kiriyama9393",
    "lance_dl",
    "borti666",
    "okoncza1",
    "tomcixleague",
    "clini0",
    "egzonmi13",
    "onawrocka",
    "croesus123",
    "pioterpioter29",
    "shindrak",
    "diegolasjv",
    "ria_vam",
    "allvaro_00",
    "gr33ngaming440",
    "klusska",
    "trurid3r",
    "mrozek3081",
    "shanyr",
    "caranesir_",
    "deadpool7360",
    "munoz32489",
    "slamhardofc",
    "sviatboiko",
    "kubi_wow",
    "maciej_33",
    "nogoth12",
    "igor_yt21",
    "duszolap666",
    "rerusiek",
    "168in1",
    "the_gofr",
    "hdrus",
    "the_deadwoodninja",
    "avaloneaa",
    "stonogaluckaa",
    "achosas",
    "klon213",
    "uzytkownikprzemo",
    "blazendragon710",
    "1nsomne",
    "sreberkos",
    "sqruel",
    "deestintv",
    "hellcat_tlc",
    "jezyk91",
    "baiwo808",
    "dopaamiine",
    "megadream777",
    "dammytee_1",
    "isadorea",
    "mormo667",
    "zmrozikus",
    "babciaania1",
    "malutkaa69",
    "ichinio",
    "thepellenator27",
    "pughealer",
    "whitejayboy",
    "limek0667",
    "andreirupefilmu",
    "patrykpeole",
    "tr3v3",
    "achtenbob",
    "capturedbyswifty",
    "sjfzvotsvofx",
    "20seconds2live",
    "omayakaboom",
    "swiftdaddy12",
    "teercess",
    "davidoomg",
    "l2mcc",
    "xpomyluna",
    "elliesabbet",
    "just__chester",
    "marmaras00",
    "vi2_tv",
    "bonon14",
    "jhing3rz",
    "babymooreekxd",
    "the_dawid_1",
    "korro1203",
    "rosjaninfyodor",
    "facexxsnatcher_popg",
    "lessismore32",
    "aliantidota",
    "laribsma",
    "zvo_isme",
    "drstaachu",
    "bzykupl91",
    "constantineaoc",
    "gonzy134gaming",
    "noobmario20",
    "uniqery",
    "krawczun1"
  ],
  "subscribers": [
    "kranik1606",
    "just__chester",
    "rhazielo",
    "xarbit",
    "palka666666",
    "nogoth12",
    "1nsomne",
    "sqruel",
    "almightly"
  ],
  "moderators": [
    "juuxxyy",
    "icequeen997",
    "nogoth12",
    "instreamly",
    "streamelements",
    "kranikbot",
    "sniffurious"
  ],
  "vips": [
    "sqruel",
    "uniqery",
    "xarbit"
  ],
  "trusted_users": [
    "kranik1606",
    "juuxxyy",
    "xarbit",
    "icequeen997",
    "nogoth12",
    "instreamly",
    "sqruel",
    "streamelements",
    "uniqery",
    "kranikbot",
    "sniffurious"
  ],
  "spotify_enabled": true,
  "last_updated": "2025-08-05T23:50:49.279612"
}